torch_mtcnn/__init__.py
torch_mtcnn/box_utils.py
torch_mtcnn/detector.py
torch_mtcnn/first_stage.py
torch_mtcnn/get_nets.py
torch_mtcnn/visualization_utils.py
torch_mtcnn-0.0.7.dist-info/LICENSE
torch_mtcnn-0.0.7.dist-info/METADATA
torch_mtcnn-0.0.7.dist-info/WHEEL
torch_mtcnn-0.0.7.dist-info/top_level.txt
torch_mtcnn-0.0.7.dist-info/RECORD
