Metadata-Version: 2.1
Name: torch-mtcnn
Version: 0.0.7
Summary: Implementation of MTCNN using Pytorch.
Home-page: https://github.com/khrlimam/mtcnn-pytorch
Author: Dan Antoshchenko
License: UNKNOWN
Platform: UNKNOWN
Classifier: Programming Language :: Python :: 3
Classifier: License :: OSI Approved :: MIT License
Classifier: Operating System :: OS Independent
Requires-Dist: numpy
Requires-Dist: torch
Requires-Dist: torchvision
